cbd_client/__init__.py
cbd_client/client.py
cbd_client-0.0.4.dist-info/LICENSE
cbd_client-0.0.4.dist-info/METADATA
cbd_client-0.0.4.dist-info/WHEEL
cbd_client-0.0.4.dist-info/top_level.txt
cbd_client-0.0.4.dist-info/RECORD
