Metadata-Version: 2.1
Name: cbd-client
Version: 0.0.4
Summary: Package for remote connection with Cyber Bullying Detector
Home-page: https://github.com/anty-filidor/CBD
Author: Michał Czuba
Author-email: michal.czuba.1995@gmail.com
License: UNKNOWN
Platform: UNKNOWN
Classifier: Programming Language :: Python :: 3.6
Classifier: License :: OSI Approved :: MIT License
Requires-Python: >=3.8
Requires-Dist: requests (==2.25.1)
